steampipe_mcp_server/__init__.py
steampipe_mcp_server/__main__.py
steampipe_mcp_server/cli.py
steampipe_mcp_server/database.py
steampipe_mcp_server/py.typed
steampipe_mcp_server/server.py
steampipe_mcp_server/test_utils.py
steampipe_mcp_server/tools.py
steampipe_mcp_server-0.2.1.dist-info/METADATA
steampipe_mcp_server-0.2.1.dist-info/WHEEL
steampipe_mcp_server-0.2.1.dist-info/entry_points.txt
steampipe_mcp_server-0.2.1.dist-info/licenses/LICENSE
steampipe_mcp_server-0.2.1.dist-info/RECORD
